wos_api_wrapper/__init__.py
wos_api_wrapper/wos/__init__.py
wos_api_wrapper/wos/article_detail.py
wos_api_wrapper/wos/user_query_search.py
wos_api_wrapper/wos/superclasses/__init__.py
wos_api_wrapper/wos/superclasses/base.py
wos_api_wrapper/wos/utils/__init__.py
wos_api_wrapper/wos/utils/cache_manager.py
wos_api_wrapper/wos/utils/config_manager.py
wos_api_wrapper/wos/utils/constants.py
wos_api_wrapper/wos/utils/exception.py
wos_api_wrapper/wos/utils/patterns.py
wos_api_wrapper-0.4.4.dist-info/LICENSE
wos_api_wrapper-0.4.4.dist-info/METADATA
wos_api_wrapper-0.4.4.dist-info/WHEEL
wos_api_wrapper-0.4.4.dist-info/top_level.txt
wos_api_wrapper-0.4.4.dist-info/RECORD
